inspect_pe/__init__.py
inspect_pe/__main__.py
inspect_pe-1.0.1.dist-info/METADATA
inspect_pe-1.0.1.dist-info/WHEEL
inspect_pe-1.0.1.dist-info/entry_points.txt
inspect_pe-1.0.1.dist-info/top_level.txt
inspect_pe-1.0.1.dist-info/RECORD
