Metadata-Version: 2.4
Name: inspect-pe
Version: 1.0.1
Summary: Swiss Army Knife for PE (Portable Executable) Analysis
Author: Abel Benedict
License: MIT
Classifier: Programming Language :: Python :: 3
Classifier: Operating System :: OS Independent
Requires-Python: >=3.9
Requires-Dist: pefile
Requires-Dist: ssdeep
Requires-Dist: lief
Requires-Dist: capstone
Requires-Dist: rich
Requires-Dist: yara-python
